{
  "mapFile": "/maps/20250313_092546.jpg",
  "scaled": true,
  "sP": {
    "p1": {
      "x": 722.3464160879267,
      "y": 396.64465367104697
    },
    "p2": {
      "x": 2491.452342023629,
      "y": 423.4490405099471
    },
    "dist": 1769.3089759379588
  },
  "scale": 0.529867882178694,
  "cP": [
    {
      "start": {
        "x": 468.15160335909144,
        "y": 300.0085499500003
      },
      "ziel": {
        "x": 707.205588105182,
        "y": 755.5235581386628
      },
      "route": [
        {
          "length": 335,
          "noA": 1,
          "rP": [
            {
              "x": 468.55387170562415,
              "y": 296.67294047510023
            },
            {
              "x": 680.7080183592241,
              "y": 508.3791237685508
            },
            {
              "x": 825.2867518952985,
              "y": 655.6566603306319
            },
            {
              "x": 798.6842649246609,
              "y": 684.1868637484172
            },
            {
              "x": 792.5155722937883,
              "y": 692.6688161158669
            },
            {
              "x": 791.7444857149293,
              "y": 738.9340108474107
            },
            {
              "x": 778.2504705848955,
              "y": 759.3678051871759
            },
            {
              "x": 733.5274490110698,
              "y": 758.9822618977463
            },
            {
              "x": 706.8028717056243,
              "y": 755.8679404751006
            }
          ]
        },
        {
          "length": 318,
          "noA": 3,
          "rP": [
            {
              "x": 468.55387170562415,
              "y": 296.67294047510023
            },
            {
              "x": 428.07399239862957,
              "y": 333.4696225443973
            },
            {
              "x": 490.1661247045451,
              "y": 417.5762381224101
            },
            {
              "x": 488.4727029143838,
              "y": 427.17229493332434
            },
            {
              "x": 451.7818974608882,
              "y": 471.7657354075727
            },
            {
              "x": 460.2490064116949,
              "y": 486.44205758897095
            },
            {
              "x": 572.5793184923966,
              "y": 604.9815829002642
            },
            {
              "x": 570.2718944792458,
              "y": 654.4296022181815
            },
            {
              "x": 580.4362175642062,
              "y": 676.8612117849906
            },
            {
              "x": 588.1470833527968,
              "y": 683.520595875137
            },
            {
              "x": 642.8241316718941,
              "y": 696.1383762564672
            },
            {
              "x": 654.7409242542614,
              "y": 704.5502298440206
            },
            {
              "x": 655.7924059527055,
              "y": 740.651101490604
            },
            {
              "x": 658.2458632490752,
              "y": 756.7738208667481
            },
            {
              "x": 706.8028717056243,
              "y": 755.8679404751006
            }
          ]
        },
        {
          "length": 326,
          "noA": 1,
          "rP": [
            {
              "x": 468.55387170562415,
              "y": 296.67294047510023
            },
            {
              "x": 681.8943280509211,
              "y": 509.19110948054043
            },
            {
              "x": 664.9601101493078,
              "y": 556.6069196050578
            },
            {
              "x": 684.1522237711362,
              "y": 579.7503507372626
            },
            {
              "x": 745.679882146998,
              "y": 642.9714309032856
            },
            {
              "x": 776.7259482999557,
              "y": 675.7109188464048
            },
            {
              "x": 792.5312183414615,
              "y": 707.3214589294163
            },
            {
              "x": 791.9667444114077,
              "y": 740.6254208025891
            },
            {
              "x": 778.9838440201709,
              "y": 760.9464822845251
            },
            {
              "x": 734.3904035459224,
              "y": 759.8175344244177
            },
            {
              "x": 706.8028717056243,
              "y": 755.8679404751006
            }
          ]
        },
        {
          "length": 320,
          "noA": 4,
          "rP": [
            {
              "x": 468.55387170562415,
              "y": 296.67294047510023
            },
            {
              "x": 538.5179498172616,
              "y": 364.6857833867734
            },
            {
              "x": 523.8416276358635,
              "y": 409.2792238610218
            },
            {
              "x": 642.9456268772104,
              "y": 536.8503320531755
            },
            {
              "x": 640.1232572269416,
              "y": 546.4463888640897
            },
            {
              "x": 570.1284899002732,
              "y": 650.3095919939848
            },
            {
              "x": 583.11139029151,
              "y": 680.226710286835
            },
            {
              "x": 594.4008688925855,
              "y": 684.7425017272652
            },
            {
              "x": 651.9772097580709,
              "y": 698.2898760485559
            },
            {
              "x": 654.235105478286,
              "y": 707.8859328594701
            },
            {
              "x": 658.1864229886625,
              "y": 756.9951647741487
            },
            {
              "x": 706.8028717056243,
              "y": 755.8679404751006
            }
          ]
        }
      ]
    },
    {
      "start": {
        "x": 706.8028717056243,
        "y": 755.8679404751006
      },
      "ziel": {
        "x": 674.8588717056243,
        "y": 890.2989404751007
      },
      "route": [
        {
          "length": 128,
          "noA": 1,
          "rP": [
            {
              "x": 706.8028717056243,
              "y": 755.8679404751006
            },
            {
              "x": 782.6483347932297,
              "y": 769.1626031192603
            },
            {
              "x": 788.2562371849319,
              "y": 804.2119930673996
            },
            {
              "x": 780.8958652958227,
              "y": 841.7148403119086
            },
            {
              "x": 674.8588717056243,
              "y": 890.2989404751007
            }
          ]
        },
        {
          "length": 179,
          "noA": 2,
          "rP": [
            {
              "x": 706.8028717056243,
              "y": 755.8679404751006
            },
            {
              "x": 557.9817452256572,
              "y": 769.5130970187417
            },
            {
              "x": 560.7856964215083,
              "y": 848.7247183015364
            },
            {
              "x": 660.6764577737051,
              "y": 848.7247183015364
            },
            {
              "x": 666.6348540648888,
              "y": 854.68311459272
            },
            {
              "x": 674.8588717056243,
              "y": 890.2989404751007
            }
          ]
        }
      ]
    },
    {
      "start": {
        "x": 674.8588717056243,
        "y": 890.2989404751007
      },
      "ziel": {
        "x": 292.861871705624,
        "y": 456.3929404751004
      },
      "route": [
        {
          "length": 363,
          "noA": 4,
          "rP": [
            {
              "x": 674.8588717056243,
              "y": 890.2989404751007
            },
            {
              "x": 667.6736686782741,
              "y": 854.56805602456
            },
            {
              "x": 659.9628028896834,
              "y": 847.2427335253989
            },
            {
              "x": 561.7162984968865,
              "y": 848.9840717922009
            },
            {
              "x": 546.4591746271271,
              "y": 752.1114817547488
            },
            {
              "x": 353.973564478789,
              "y": 731.0001567707375
            },
            {
              "x": 344.0388233098425,
              "y": 674.4963163723543
            },
            {
              "x": 320.4438130335946,
              "y": 611.1623414203204
            },
            {
              "x": 320.4438130335946,
              "y": 598.1229936360783
            },
            {
              "x": 354.5944858018481,
              "y": 559.0049502833515
            },
            {
              "x": 350.8689578634932,
              "y": 548.4492877913458
            },
            {
              "x": 286.9140615884002,
              "y": 480.7688635778979
            },
            {
              "x": 292.861871705624,
              "y": 456.3929404751004
            }
          ]
        },
        {
          "length": 422,
          "noA": 4,
          "rP": [
            {
              "x": 674.8588717056243,
              "y": 890.2989404751007
            },
            {
              "x": 780.4223291558169,
              "y": 840.661071636215
            },
            {
              "x": 787.9354771648327,
              "y": 798.5874427857266
            },
            {
              "x": 782.6762735585216,
              "y": 769.286165550565
            },
            {
              "x": 657.2067018079581,
              "y": 755.7624991343366
            },
            {
              "x": 652.6988130025487,
              "y": 697.9112594649151
            },
            {
              "x": 582.8265365187019,
              "y": 680.6310190441789
            },
            {
              "x": 571.5568145051783,
              "y": 654.3350010126236
            },
            {
              "x": 574.5620737087846,
              "y": 604.7482241531194
            },
            {
              "x": 481.39903839698894,
              "y": 513.8391332440285
            },
            {
              "x": 435.56883554199266,
              "y": 492.05100401788275
            },
            {
              "x": 408.52150270953587,
              "y": 492.80231881878433
            },
            {
              "x": 331.13607821667335,
              "y": 428.18924594124866
            },
            {
              "x": 292.861871705624,
              "y": 456.3929404751004
            }
          ]
        }
      ]
    },
    {
      "start": {
        "x": 292.861871705624,
        "y": 456.3929404751004
      },
      "ziel": {
        "x": 484.5258717056242,
        "y": 419.12494047510035
      },
      "route": [
        {
          "length": 139,
          "noA": 1,
          "rP": [
            {
              "x": 292.861871705624,
              "y": 456.3929404751004
            },
            {
              "x": 290.09243766883907,
              "y": 473.0584289421366
            },
            {
              "x": 368.1263994493763,
              "y": 541.3381455001066
            },
            {
              "x": 469.0616326220277,
              "y": 444.2197908928076
            },
            {
              "x": 484.5258717056242,
              "y": 419.12494047510035
            }
          ]
        },
        {
          "length": 133,
          "noA": 1,
          "rP": [
            {
              "x": 292.861871705624,
              "y": 456.3929404751004
            },
            {
              "x": 421.1386017459369,
              "y": 339.4676791548039
            },
            {
              "x": 427.0759684031517,
              "y": 345.40504581201867
            },
            {
              "x": 477.5435849894774,
              "y": 394.6003695432269
            },
            {
              "x": 484.5258717056242,
              "y": 419.12494047510035
            }
          ]
        },
        {
          "length": 129,
          "noA": 2,
          "rP": [
            {
              "x": 292.861871705624,
              "y": 456.3929404751004
            },
            {
              "x": 378.7288399086884,
              "y": 378.4846600450725
            },
            {
              "x": 455.91460645248065,
              "y": 452.2776456418848
            },
            {
              "x": 466.9411445301653,
              "y": 448.4607670765325
            },
            {
              "x": 484.5258717056242,
              "y": 419.12494047510035
            }
          ]
        }
      ]
    },
    {
      "start": {
        "x": 484.5258717056242,
        "y": 419.12494047510035
      },
      "ziel": {
        "x": 576.3648717056243,
        "y": 673.3459404751005
      },
      "route": [
        {
          "length": 150,
          "noA": 1,
          "rP": [
            {
              "x": 484.5258717056242,
              "y": 419.12494047510035
            },
            {
              "x": 451.64725903065033,
              "y": 473.18264416587476
            },
            {
              "x": 575.3183655242507,
              "y": 605.0642805511663
            },
            {
              "x": 570.1867843419436,
              "y": 648.1695624825458
            },
            {
              "x": 576.3648717056243,
              "y": 673.3459404751005
            }
          ]
        },
        {
          "length": 180,
          "noA": 1,
          "rP": [
            {
              "x": 484.5258717056242,
              "y": 419.12494047510035
            },
            {
              "x": 522.4630793464879,
              "y": 412.11682809642065
            },
            {
              "x": 646.1341858400882,
              "y": 538.8668832994052
            },
            {
              "x": 639.9762884213197,
              "y": 550.6695200187115
            },
            {
              "x": 570.1867843419436,
              "y": 644.0642975367001
            },
            {
              "x": 576.3648717056243,
              "y": 673.3459404751005
            }
          ]
        }
      ]
    },
    {
      "start": {
        "x": 576.3648717056243,
        "y": 673.3459404751005
      },
      "ziel": {
        "x": 250.269871705624,
        "y": 861.0169404751007
      },
      "route": [
        {
          "length": 216,
          "noA": 1,
          "rP": [
            {
              "x": 576.3648717056243,
              "y": 673.3459404751005
            },
            {
              "x": 559.4104638590987,
              "y": 689.2222119410023
            },
            {
              "x": 550.173617730946,
              "y": 806.7354210158342
            },
            {
              "x": 281.2787637780557,
              "y": 840.6038568190608
            },
            {
              "x": 250.269871705624,
              "y": 861.0169404751007
            }
          ]
        },
        {
          "length": 222,
          "noA": 1,
          "rP": [
            {
              "x": 576.3648717056243,
              "y": 673.3459404751005
            },
            {
              "x": 529.134134883487,
              "y": 680.4985239310803
            },
            {
              "x": 362.8709045767381,
              "y": 665.6169385023898
            },
            {
              "x": 347.98931914804757,
              "y": 695.8932674780015
            },
            {
              "x": 347.47616102981686,
              "y": 762.6038228479933
            },
            {
              "x": 339.26563113812557,
              "y": 803.6564723064499
            },
            {
              "x": 250.269871705624,
              "y": 861.0169404751007
            }
          ]
        }
      ]
    },
    {
      "start": {
        "x": 250.269871705624,
        "y": 861.0169404751007
      },
      "ziel": {
        "x": 196.0398429411614,
        "y": 580.186371872608
      },
      "route": [
        {
          "length": 187,
          "noA": 1,
          "rP": [
            {
              "x": 250.269871705624,
              "y": 861.0169404751007
            },
            {
              "x": 99.9877492947324,
              "y": 717.7558405523591
            },
            {
              "x": 151.7418650939482,
              "y": 604.9809472366719
            },
            {
              "x": 159.27313896710208,
              "y": 593.684036426941
            },
            {
              "x": 170.28038539709624,
              "y": 579.78014619958
            },
            {
              "x": 196.0398429411614,
              "y": 580.186371872608
            }
          ]
        },
        {
          "length": 198,
          "noA": 1,
          "rP": [
            {
              "x": 250.269871705624,
              "y": 861.0169404751007
            },
            {
              "x": 339.3322830483639,
              "y": 802.5337922033714
            },
            {
              "x": 347.4286921263841,
              "y": 762.8228333921297
            },
            {
              "x": 346.27206225809545,
              "y": 676.4611365599146
            },
            {
              "x": 288.44056884366574,
              "y": 647.9309331421293
            },
            {
              "x": 250.65732647957162,
              "y": 624.7983357763574
            },
            {
              "x": 196.0398429411614,
              "y": 580.186371872608
            }
          ]
        }
      ]
    },
    {
      "start": {
        "x": 196.0398429411614,
        "y": 580.186371872608
      },
      "ziel": {
        "x": 149.18850674669787,
        "y": 670.5022006812125
      },
      "route": [
        {
          "length": 57,
          "noA": 1,
          "rP": [
            {
              "x": 196.0398429411614,
              "y": 580.186371872608
            },
            {
              "x": 167.76551925222233,
              "y": 582.0030306496794
            },
            {
              "x": 149.18850674669787,
              "y": 670.5022006812125
            }
          ]
        }
      ]
    },
    {
      "start": {
        "x": 149.18850674669787,
        "y": 670.5022006812125
      },
      "ziel": {
        "x": 468.68075115713594,
        "y": 526.5613485174991
      },
      "route": [
        {
          "length": 221,
          "noA": 2,
          "rP": [
            {
              "x": 149.18850674669787,
              "y": 670.5022006812125
            },
            {
              "x": 187.23545536841368,
              "y": 622.5621846976661
            },
            {
              "x": 266.11761238569585,
              "y": 638.6778941958206
            },
            {
              "x": 317.857521827139,
              "y": 599.660913305552
            },
            {
              "x": 419.6409502365354,
              "y": 503.8148515533704
            },
            {
              "x": 435.7566597346898,
              "y": 490.66782538382336
            },
            {
              "x": 469.6844692044886,
              "y": 499.99797298801803
            },
            {
              "x": 493.43393583334773,
              "y": 521.2028539066423
            },
            {
              "x": 468.68075115713594,
              "y": 526.5613485174991
            }
          ]
        },
        {
          "length": 219,
          "noA": 1,
          "rP": [
            {
              "x": 149.18850674669787,
              "y": 670.5022006812125
            },
            {
              "x": 293.2598599615349,
              "y": 726.8901988172975
            },
            {
              "x": 341.1828908376257,
              "y": 731.5552726193947
            },
            {
              "x": 351.7853312969378,
              "y": 661.5791655879348
            },
            {
              "x": 356.8745027174076,
              "y": 648.0080418000152
            },
            {
              "x": 460.7784192186664,
              "y": 550.8896871927162
            },
            {
              "x": 468.68075115713594,
              "y": 526.5613485174991
            }
          ]
        },
        {
          "length": 193,
          "noA": 1,
          "rP": [
            {
              "x": 149.18850674669787,
              "y": 670.5022006812125
            },
            {
              "x": 187.45288767276764,
              "y": 622.0483344521223
            },
            {
              "x": 265.91094707167736,
              "y": 638.5881415686491
            },
            {
              "x": 357.09193502176157,
              "y": 648.3423867912163
            },
            {
              "x": 461.8440467597653,
              "y": 551.6481298022898
            },
            {
              "x": 468.68075115713594,
              "y": 526.5613485174991
            }
          ]
        }
      ]
    },
    {
      "start": {
        "x": 468.68075115713594,
        "y": 526.5613485174991
      },
      "ziel": {
        "x": 892.6006726275228,
        "y": 816.136474635087
      },
      "route": [
        {
          "length": 306,
          "noA": 3,
          "rP": [
            {
              "x": 468.68075115713594,
              "y": 526.5613485174991
            },
            {
              "x": 494.0031766778642,
              "y": 525.1317613758989
            },
            {
              "x": 590.570204381279,
              "y": 596.9738979281979
            },
            {
              "x": 666.6109073554655,
              "y": 559.1868001312095
            },
            {
              "x": 775.7736343245432,
              "y": 673.481108282594
            },
            {
              "x": 792.5679000120936,
              "y": 706.1366248972754
            },
            {
              "x": 792.1013926318838,
              "y": 742.9907079338443
            },
            {
              "x": 783.2377524078988,
              "y": 774.2467024078965
            },
            {
              "x": 789.3023483506254,
              "y": 813.4333223455141
            },
            {
              "x": 892.6006726275228,
              "y": 816.136474635087
            }
          ]
        },
        {
          "length": 303,
          "noA": 5,
          "rP": [
            {
              "x": 468.68075115713594,
              "y": 526.5613485174991
            },
            {
              "x": 499.50329869053695,
              "y": 524.1133757649011
            },
            {
              "x": 576.4975427498722,
              "y": 604.8331477625912
            },
            {
              "x": 572.1510934884581,
              "y": 644.5721124383772
            },
            {
              "x": 579.602149365168,
              "y": 681.2064704988674
            },
            {
              "x": 654.1127081322666,
              "y": 697.3504248984054
            },
            {
              "x": 658.4591573936807,
              "y": 756.3379505890251
            },
            {
              "x": 783.88526465163,
              "y": 766.8936130810308
            },
            {
              "x": 790.0944778822216,
              "y": 814.0836336335266
            },
            {
              "x": 892.6006726275228,
              "y": 816.136474635087
            }
          ]
        }
      ]
    },
    {
      "start": {
        "x": 892.6006726275228,
        "y": 816.136474635087
      },
      "ziel": {
        "x": 1431.1088018988264,
        "y": 545.1889882092738
      },
      "route": [
        {
          "length": 351,
          "noA": 1,
          "rP": [
            {
              "x": 892.6006726275228,
              "y": 816.136474635087
            },
            {
              "x": 973.7076449082407,
              "y": 790.1357008144213
            },
            {
              "x": 1001.8050897426994,
              "y": 728.4371879305069
            },
            {
              "x": 1042.937431665309,
              "y": 687.5945103876338
            },
            {
              "x": 1141.5153803577173,
              "y": 591.8866007722169
            },
            {
              "x": 1176.5647703058564,
              "y": 558.5896803214846
            },
            {
              "x": 1306.7206737095796,
              "y": 466.5698040094648
            },
            {
              "x": 1342.4710514566816,
              "y": 448.34412123643244
            },
            {
              "x": 1432.303338881562,
              "y": 536.3643552009936
            },
            {
              "x": 1431.1088018988264,
              "y": 545.1889882092738
            }
          ]
        },
        {
          "length": 381,
          "noA": 1,
          "rP": [
            {
              "x": 892.6006726275228,
              "y": 816.136474635087
            },
            {
              "x": 970.0538065262424,
              "y": 836.0456517515671
            },
            {
              "x": 1134.5979571369185,
              "y": 832.3201238132121
            },
            {
              "x": 1190.700739252144,
              "y": 827.835095400811
            },
            {
              "x": 1241.5924534568423,
              "y": 804.7024980350391
            },
            {
              "x": 1325.969797532693,
              "y": 800.1936463738188
            },
            {
              "x": 1387.2711805519884,
              "y": 762.4104040097245
            },
            {
              "x": 1402.6929121291698,
              "y": 716.1452092781808
            },
            {
              "x": 1430.3575152421693,
              "y": 672.1885728094994
            },
            {
              "x": 1492.0444415508944,
              "y": 603.5618672910427
            },
            {
              "x": 1438.4539243201893,
              "y": 544.5737440083244
            },
            {
              "x": 1431.1088018988264,
              "y": 545.1889882092738
            }
          ]
        },
        {
          "length": 363,
          "noA": 3,
          "rP": [
            {
              "x": 892.6006726275228,
              "y": 816.136474635087
            },
            {
              "x": 1149.4312984365092,
              "y": 792.7623142830241
            },
            {
              "x": 1213.78132646264,
              "y": 780.343887821841
            },
            {
              "x": 1220.5550136232853,
              "y": 714.8649119356028
            },
            {
              "x": 1368.9360406845567,
              "y": 695.3277000889963
            },
            {
              "x": 1421.1914947890552,
              "y": 659.6410485054363
            },
            {
              "x": 1430.7504193203658,
              "y": 647.5330774324427
            },
            {
              "x": 1453.054576560091,
              "y": 616.6258881145382
            },
            {
              "x": 1456.2408847371944,
              "y": 606.1110711300964
            },
            {
              "x": 1473.765579711264,
              "y": 584.4441755257922
            },
            {
              "x": 1439.0348205808352,
              "y": 544.2966924942872
            },
            {
              "x": 1431.1088018988264,
              "y": 545.1889882092738
            }
          ]
        }
      ]
    },
    {
      "start": {
        "x": 1431.1088018988264,
        "y": 545.1889882092738
      },
      "ziel": {
        "x": 1609.48256379582,
        "y": 718.4824847357835
      },
      "route": [
        {
          "length": 156,
          "noA": 2,
          "rP": [
            {
              "x": 1431.1088018988264,
              "y": 545.1889882092738
            },
            {
              "x": 1443.6631291980138,
              "y": 546.1491529237144
            },
            {
              "x": 1506.7520311046644,
              "y": 591.7133598562954
            },
            {
              "x": 1548.4926682247212,
              "y": 579.6053887833018
            },
            {
              "x": 1644.3275150674456,
              "y": 678.6265069894206
            },
            {
              "x": 1612.46443329641,
              "y": 711.2795825233744
            },
            {
              "x": 1609.48256379582,
              "y": 718.4824847357835
            }
          ]
        },
        {
          "length": 175,
          "noA": 2,
          "rP": [
            {
              "x": 1431.1088018988264,
              "y": 545.1889882092738
            },
            {
              "x": 1445.8563196206176,
              "y": 546.7734874619632
            },
            {
              "x": 1495.591403957027,
              "y": 602.2917211398158
            },
            {
              "x": 1487.1094515895775,
              "y": 634.2918141624668
            },
            {
              "x": 1462.820224355517,
              "y": 659.3521279753865
            },
            {
              "x": 1554.965070529175,
              "y": 761.5210996742122
            },
            {
              "x": 1609.48256379582,
              "y": 718.4824847357835
            }
          ]
        }
      ]
    },
    {
      "start": {
        "x": 1609.48256379582,
        "y": 718.4824847357835
      },
      "ziel": {
        "x": 1697.5404968842092,
        "y": 626.4732341370178
      },
      "route": [
        {
          "length": 61,
          "noA": 0,
          "rP": [
            {
              "x": 1609.48256379582,
              "y": 718.4824847357835
            },
            {
              "x": 1697.5404968842092,
              "y": 626.4732341370178
            }
          ]
        }
      ]
    },
    {
      "start": {
        "x": 1697.5404968842092,
        "y": 626.4732341370178
      },
      "ziel": {
        "x": 1437.318015129418,
        "y": 344.80074304018285
      },
      "route": [
        {
          "length": 228,
          "noA": 1,
          "rP": [
            {
              "x": 1697.5404968842092,
              "y": 626.4732341370178
            },
            {
              "x": 1732.886381020635,
              "y": 589.5542042715675
            },
            {
              "x": 1659.0933954238228,
              "y": 515.3371210563827
            },
            {
              "x": 1559.0063574879164,
              "y": 515.3371210563827
            },
            {
              "x": 1437.4547725235425,
              "y": 388.7422736712499
            },
            {
              "x": 1437.318015129418,
              "y": 344.80074304018285
            }
          ]
        },
        {
          "length": 253,
          "noA": 2,
          "rP": [
            {
              "x": 1697.5404968842092,
              "y": 626.4732341370178
            },
            {
              "x": 1731.558159908274,
              "y": 591.2837886080388
            },
            {
              "x": 1663.821288301821,
              "y": 503.02059227235725
            },
            {
              "x": 1689.4791942133563,
              "y": 435.283720665904
            },
            {
              "x": 1589.9265192765993,
              "y": 365.4942165865279
            },
            {
              "x": 1530.4001775618372,
              "y": 329.57314831037843
            },
            {
              "x": 1502.9366664507427,
              "y": 315.3968059337858
            },
            {
              "x": 1437.318015129418,
              "y": 344.80074304018285
            }
          ]
        },
        {
          "length": 226,
          "noA": 1,
          "rP": [
            {
              "x": 1697.5404968842092,
              "y": 626.4732341370178
            },
            {
              "x": 1654.4790062384711,
              "y": 669.8883522709064
            },
            {
              "x": 1557.49734425197,
              "y": 569.9625415287614
            },
            {
              "x": 1555.1840845153927,
              "y": 520.6130004817815
            },
            {
              "x": 1437.6119208849743,
              "y": 388.90609417046215
            },
            {
              "x": 1437.318015129418,
              "y": 344.80074304018285
            }
          ]
        }
      ]
    },
    {
      "start": {
        "x": 1437.318015129418,
        "y": 344.80074304018285
      },
      "ziel": {
        "x": 1244.267931051026,
        "y": 311.49678116700994
      },
      "route": [
        {
          "length": 117,
          "noA": 1,
          "rP": [
            {
              "x": 1437.318015129418,
              "y": 344.80074304018285
            },
            {
              "x": 1355.4033203062565,
              "y": 402.4401552345491
            },
            {
              "x": 1244.267931051026,
              "y": 311.49678116700994
            }
          ]
        },
        {
          "length": 145,
          "noA": 1,
          "rP": [
            {
              "x": 1437.318015129418,
              "y": 344.80074304018285
            },
            {
              "x": 1458.883139189143,
              "y": 320.2269041965958
            },
            {
              "x": 1465.4142425120795,
              "y": 297.83454994652857
            },
            {
              "x": 1359.9835745846797,
              "y": 260.98046690995966
            },
            {
              "x": 1343.1893088971292,
              "y": 256.78190048807204
            },
            {
              "x": 1307.2682406209797,
              "y": 260.5139595297499
            },
            {
              "x": 1286.7419158917514,
              "y": 272.64315141520296
            },
            {
              "x": 1244.267931051026,
              "y": 311.49678116700994
            }
          ]
        }
      ]
    },
    {
      "start": {
        "x": 1244.267931051026,
        "y": 311.49678116700994
      },
      "ziel": {
        "x": 1250.2561741296024,
        "y": 791.1028964925111
      },
      "route": [
        {
          "length": 340,
          "noA": 3,
          "rP": [
            {
              "x": 1244.267931051026,
              "y": 311.49678116700994
            },
            {
              "x": 1274.3180040968398,
              "y": 333.4346988388903
            },
            {
              "x": 1335.724351893552,
              "y": 401.11589278951567
            },
            {
              "x": 1332.132245065937,
              "y": 433.4448542380502
            },
            {
              "x": 1295.6980186715568,
              "y": 476.03697805119884
            },
            {
              "x": 1288.0006468980962,
              "y": 496.5633027804271
            },
            {
              "x": 1280.3032751246358,
              "y": 513.4975206820404
            },
            {
              "x": 1402.0955930679747,
              "y": 655.9304590647345
            },
            {
              "x": 1416.4177516787645,
              "y": 683.3641528328095
            },
            {
              "x": 1389.0792275192157,
              "y": 711.4036647913208
            },
            {
              "x": 1386.625770222846,
              "y": 765.3797253114552
            },
            {
              "x": 1250.2561741296024,
              "y": 791.1028964925111
            }
          ]
        },
        {
          "length": 370,
          "noA": 2,
          "rP": [
            {
              "x": 1244.267931051026,
              "y": 311.49678116700994
            },
            {
              "x": 1189.5638156111677,
              "y": 356.57344698909134
            },
            {
              "x": 1106.2361740566291,
              "y": 435.80300781143956
            },
            {
              "x": 1234.6427036652624,
              "y": 562.1604970539777
            },
            {
              "x": 1385.5886773009431,
              "y": 711.7404437789281
            },
            {
              "x": 1388.3207311224032,
              "y": 763.6494663866736
            },
            {
              "x": 1250.2561741296024,
              "y": 791.1028964925111
            }
          ]
        }
      ]
    },
    {
      "start": {
        "x": 1250.2561741296024,
        "y": 791.1028964925111
      },
      "ziel": {
        "x": 1168.8628773440869,
        "y": 791.5816805912494
      },
      "route": [
        {
          "length": 39,
          "noA": 0,
          "rP": [
            {
              "x": 1250.2561741296024,
              "y": 791.1028964925111
            },
            {
              "x": 1168.8628773440869,
              "y": 791.5816805912494
            }
          ]
        }
      ]
    },
    {
      "start": {
        "x": 1168.8628773440869,
        "y": 791.5816805912494
      },
      "ziel": {
        "x": 1128.1662289513292,
        "y": 605.8134502807786
      },
      "route": [
        {
          "length": 154,
          "noA": 3,
          "rP": [
            {
              "x": 1168.8628773440869,
              "y": 791.5816805912494
            },
            {
              "x": 1214.4788422451925,
              "y": 780.7685944263933
            },
            {
              "x": 1214.902939863565,
              "y": 760.8360063628866
            },
            {
              "x": 1220.8403065207797,
              "y": 714.1852683419132
            },
            {
              "x": 1223.8089898493872,
              "y": 680.2574588721144
            },
            {
              "x": 1231.0186493617193,
              "y": 640.3922827451009
            },
            {
              "x": 1134.324392372793,
              "y": 630.6380375225338
            },
            {
              "x": 1118.2086828746385,
              "y": 614.5223280243794
            },
            {
              "x": 1128.1662289513292,
              "y": 605.8134502807786
            }
          ]
        },
        {
          "length": 174,
          "noA": 1,
          "rP": [
            {
              "x": 1168.8628773440869,
              "y": 791.5816805912494
            },
            {
              "x": 1152.1364923444373,
              "y": 785.0095706101182
            },
            {
              "x": 1119.480975729756,
              "y": 782.4649848998832
            },
            {
              "x": 1072.4061400904102,
              "y": 776.951715861041
            },
            {
              "x": 1047.808478224806,
              "y": 772.2866420589436
            },
            {
              "x": 1002.4300330589501,
              "y": 727.3322945114603
            },
            {
              "x": 1036.7819401471215,
              "y": 691.7080945681715
            },
            {
              "x": 1097.0038019560143,
              "y": 629.7898422857887
            },
            {
              "x": 1128.1662289513292,
              "y": 605.8134502807786
            }
          ]
        }
      ]
    },
    {
      "start": {
        "x": 1128.1662289513292,
        "y": 605.8134502807786
      },
      "ziel": {
        "x": 995.0642495020742,
        "y": 690.3188437080934
      },
      "route": [
        {
          "length": 80,
          "noA": 1,
          "rP": [
            {
              "x": 1128.1662289513292,
              "y": 605.8134502807786
            },
            {
              "x": 1032.4563132979429,
              "y": 680.6113936606994
            },
            {
              "x": 1001.9633440430617,
              "y": 698.4865825342505
            },
            {
              "x": 995.0642495020742,
              "y": 690.3188437080934
            }
          ]
        }
      ]
    },
    {
      "start": {
        "x": 995.0642495020742,
        "y": 690.3188437080934
      },
      "ziel": {
        "x": 814.562644277725,
        "y": 589.0560068249372
      },
      "route": [
        {
          "length": 106,
          "noA": 1,
          "rP": [
            {
              "x": 995.0642495020742,
              "y": 690.3188437080934
            },
            {
              "x": 985.9438638612941,
              "y": 701.9095712243999
            },
            {
              "x": 897.9698950914647,
              "y": 636.7177059208609
            },
            {
              "x": 814.562644277725,
              "y": 589.0560068249372
            }
          ]
        }
      ]
    },
    {
      "start": {
        "x": 814.562644277725,
        "y": 589.0560068249372
      },
      "ziel": {
        "x": 773.626603835598,
        "y": 546.6836140865952
      },
      "route": [
        {
          "length": 28,
          "noA": 0,
          "rP": [
            {
              "x": 814.562644277725,
              "y": 589.0560068249372
            },
            {
              "x": 773.626603835598,
              "y": 546.6836140865952
            }
          ]
        }
      ]
    }
  ]
}